LICENSE.txt
MANIFEST.in
README.md
requirements-internal.txt
requirements-test.txt
requirements.txt
setup.py
odm_sdk/__init__.py
odm_sdk/bio_meta_keys.py
odm_sdk/chunked_upload.py
odm_sdk/connection.py
odm_sdk/data_importer.py
odm_sdk/exceptions.py
odm_sdk/file_filters.py
odm_sdk/file_permissions.py
odm_sdk/file_types.py
odm_sdk/files_util.py
odm_sdk/genome_query.py
odm_sdk/groups_util.py
odm_sdk/metainfo.py
odm_sdk/metainfo_scalar_values.py
odm_sdk/share_util.py
odm_sdk/shell.py
odm_sdk/unaligned_reads.py
odm_sdk/utils.py
odm_sdk/version.py
odm_sdk.egg-info/PKG-INFO
odm_sdk.egg-info/SOURCES.txt
odm_sdk.egg-info/dependency_links.txt
odm_sdk.egg-info/entry_points.txt
odm_sdk.egg-info/requires.txt
odm_sdk.egg-info/top_level.txt
odm_sdk/scripts/__init__.py
odm_sdk/scripts/delete_study_or_template.py
odm_sdk/scripts/import_ODM_data.py
odm_sdk/scripts/shell.py
odm_sdk/scripts/user_setup.py
odm_sdk/scripts/utils.py
odm_sdk/scripts/dictionaries/__init__.py
odm_sdk/scripts/dictionaries/load_init_share_dictionaries.py
odm_sdk/scripts/internal/README.md
odm_sdk/scripts/internal/__init__.py
odm_sdk/scripts/internal/generate_gene_dictionaries.py
odm_sdk/scripts/internal/generate_unit_dictionaries.py
odm_sdk/scripts/internal/upload_dictionaries_with_specific_metainfo.py
odm_sdk/scripts/internal/wait_for_host.py
odm_sdk/scripts/internal/wait_until_ready.py
odm_sdk/scripts/internal/data/disease_extension.csv
odm_sdk/scripts/metainfo_templates/__init__.py
odm_sdk/scripts/metainfo_templates/get_template.py
odm_sdk/scripts/metainfo_templates/update_template.py
odm_sdk/scripts/metainfo_templates/importers/__init__.py
odm_sdk/scripts/metainfo_templates/importers/dictionary_search.py
odm_sdk/scripts/metainfo_templates/importers/format.py
odm_sdk/scripts/metainfo_templates/importers/json_validation.py
odm_sdk/scripts/metainfo_templates/importers/template_importer.py
odm_sdk/scripts/metainfo_templates/importers/template_technical_fields.py
odm_sdk/scripts/metainfo_templates/importers/__pycache__/__init__.cpython-313.pyc
odm_sdk/scripts/metainfo_templates/importers/__pycache__/dictionary_search.cpython-313.pyc
