Metadata-Version: 2.4
Name: odm-sdk
Version: 1.61.0
Summary: SDK for interacting with the Open Data Manager
Home-page: https://github.com/genestack/sdk
Author: Genestack Limited
Author-email: 
License: MIT
Project-URL: Documentation, https://odm.demo.genestack.com/user-docs/tools/odm-sdk/installation/
Project-URL: Source, https://github.com/genestack/sdk/
Project-URL: Tracker, https://github.com/genestack/sdk/issues
Keywords: genestack,odm,import,share,create,delete,curate,genomics,api
Classifier: Development Status :: 4 - Beta
Classifier: Intended Audience :: Developers
Classifier: License :: OSI Approved :: MIT License
Classifier: Programming Language :: Python :: 3.10
Classifier: Programming Language :: Python :: 3.11
Classifier: Programming Language :: Python :: 3.12
Classifier: Topic :: Software Development
Classifier: Topic :: Scientific/Engineering :: Bio-Informatics
Classifier: Topic :: Software Development :: Libraries :: Python Modules
Requires-Python: >=3.10
License-File: LICENSE.txt
Requires-Dist: keyring==25.6.0
Requires-Dist: requests==2.32.4
Requires-Dist: pyOpenSSL==25.1.0
Requires-Dist: jsonschema==4.25.0
Requires-Dist: pyrsistent==0.20.0
Requires-Dist: odm-api==1.61.0
Dynamic: author
Dynamic: classifier
Dynamic: description-content-type
Dynamic: home-page
Dynamic: keywords
Dynamic: license
Dynamic: license-file
Dynamic: project-url
Dynamic: requires-dist
Dynamic: requires-python
Dynamic: summary
